{"data":{"site":{"siteMetadata":{"title":"Niwa-Lab Blog","author":"Niwa Takeru"}},"markdownRemark":{"id":"7444a54b-1cd6-5e58-943d-ab12f8ff2716","excerpt":"イベント概要 日時: 2018年11月8日 場所: Google 東京オフィス URL:  https://k8sjp.connpass.com/event/104450/ About: Kubernetes Meetup Tokyo #1…","html":"<h2>イベント概要</h2>\n<ul>\n<li>日時: 2018年11月8日</li>\n<li>場所: Google 東京オフィス</li>\n<li>URL: <a href=\"https://k8sjp.connpass.com/event/104450/\">https://k8sjp.connpass.com/event/104450/</a></li>\n<li>About: Kubernetes Meetup Tokyo #14を開催します！ コンテナをデプロイできる強力なシステム Kubernetes のことを詳しく聞く会です！</li>\n</ul>\n<h1>Sessions</h1>\n<h2>Quipper のマイクロサービス化への道のり</h2>\n<ul>\n<li>\n<p>Speaker: Yuya Takeyama, Quipper</p>\n<blockquote>\n<p>Quipper は現在 Kubernetes によるマイクロサービス基盤の構築・移行を行なっており、すでに半分以上のサービスは本番で稼働しています。それまでは Heroku や Deis を利用していた Quipper が何故 Kubernetes を選んだのか、どのように運用を行なっているか、そしてこれから行なっていくマイクロサービス化によって何を目指しているのかについてお話しします。</p>\n</blockquote>\n</li>\n</ul>\n<h2>CacooはなぜKubernetesによるmicroservicesへの道を選んだのか？</h2>\n<ul>\n<li>\n<p>Speaker: Kohei Kimura, Nulab</p>\n<blockquote>\n</blockquote>\n</li>\n</ul>\n<h2>Athenzを用いたKubernetes Webhook Authorization</h2>\n<ul>\n<li>Speaker: Yusuke Kato, Yahoo 株式会社</li>\n</ul>","frontmatter":{"title":"Kubernetes Metetup #14 参加レポート","date":"November 08, 2018"}}},"pageContext":{"slug":"/20181108/","previous":{"fields":{"slug":"/20181101/"},"frontmatter":{"title":"React会 #1 参加レポート"}},"next":null}}